easycmd.py
setup.py
easycmd.egg-info/PKG-INFO
easycmd.egg-info/SOURCES.txt
easycmd.egg-info/dependency_links.txt
easycmd.egg-info/top_level.txt