Metadata-Version: 1.0
Name: easycmd
Version: 0.0.1421587592
Summary: A helper function for common uses of subprocess
Home-page: UNKNOWN
Author: Mike Lang
Author-email: mikelang3000@gmail.com
License: UNKNOWN
Platform: UNKNOWN
